docprompt-0.8.8.dist-info/METADATA
docprompt-0.8.8.dist-info/WHEEL
docprompt-0.8.8.dist-info/entry_points.txt
docprompt-0.8.8.dist-info/licenses/LICENSE
docprompt/__init__.py
docprompt/_decorators.py
docprompt/_exec/__init__.py
docprompt/_exec/ghostscript.py
docprompt/_exec/tesseract.py
docprompt/_pdfium.py
docprompt/contrib/__init__.py
docprompt/contrib/parser_bot/__init__.py
docprompt/docprompt.cpython-310-x86_64-linux-gnu.so
docprompt/provenance/__init__.py
docprompt/provenance/search.py
docprompt/provenance/source.py
docprompt/provenance/util.py
docprompt/rasterize.py
docprompt/schema/__init__.py
docprompt/schema/document.py
docprompt/schema/layout.py
docprompt/schema/pipeline/__init__.py
docprompt/schema/pipeline/metadata.py
docprompt/schema/pipeline/node/__init__.py
docprompt/schema/pipeline/node/base.py
docprompt/schema/pipeline/node/collection.py
docprompt/schema/pipeline/node/document.py
docprompt/schema/pipeline/node/image.py
docprompt/schema/pipeline/node/page.py
docprompt/schema/pipeline/node/typing.py
docprompt/schema/pipeline/rasterizer.py
docprompt/storage.py
docprompt/tasks/__init__.py
docprompt/tasks/base.py
docprompt/tasks/capabilities.py
docprompt/tasks/classification/__init__.py
docprompt/tasks/classification/anthropic.py
docprompt/tasks/classification/base.py
docprompt/tasks/credentials.py
docprompt/tasks/factory.py
docprompt/tasks/markerize/__init__.py
docprompt/tasks/markerize/anthropic.py
docprompt/tasks/markerize/base.py
docprompt/tasks/message.py
docprompt/tasks/ocr/__init__.py
docprompt/tasks/ocr/amazon.py
docprompt/tasks/ocr/base.py
docprompt/tasks/ocr/gcp.py
docprompt/tasks/ocr/result.py
docprompt/tasks/ocr/tesseract.py
docprompt/tasks/parser.py
docprompt/tasks/result.py
docprompt/tasks/table_extraction/__init__.py
docprompt/tasks/table_extraction/anthropic.py
docprompt/tasks/table_extraction/base.py
docprompt/tasks/table_extraction/schema.py
docprompt/tasks/util.py
docprompt/utils/__init__.py
docprompt/utils/compressor.py
docprompt/utils/date_extraction.py
docprompt/utils/inference.py
docprompt/utils/layout.py
docprompt/utils/masking/__init__.py
docprompt/utils/masking/image.py
docprompt-0.8.8.dist-info/RECORD
