Metadata-Version: 2.1
Name: docprompt
Version: 0.8.8
Summary: Documents and large language models.
Home-page: https://github.com/Docprompt/docprompt
Author-Email: Frank Colson <frank@pageleaf.io>
License: Apache-2.0
Classifier: Development Status :: 2 - Pre-Alpha
Classifier: Intended Audience :: Developers
Classifier: License :: OSI Approved :: Apache Software License
Classifier: Natural Language :: English
Classifier: Programming Language :: Python :: 3
Classifier: Programming Language :: Python :: 3.8
Classifier: Programming Language :: Python :: 3.9
Classifier: Programming Language :: Python :: 3.10
Classifier: Programming Language :: Python :: 3.11
Classifier: Programming Language :: Python :: 3.12
Project-URL: Homepage, https://github.com/Docprompt/docprompt
Requires-Python: <3.13,>=3.8.6
Requires-Dist: pillow>=9.0.1
Requires-Dist: tqdm>=4.50.2
Requires-Dist: fsspec>=2022.11.0
Requires-Dist: pydantic>=2.1.0
Requires-Dist: tenacity>=7.0.0
Requires-Dist: pypdfium2<5.0.0,>=4.28.0
Requires-Dist: filetype>=1.2.0
Requires-Dist: beautifulsoup4>=4.12.3
Requires-Dist: pypdf>=5.0.0
Provides-Extra: google
Requires-Dist: google-cloud-documentai>=2.20.0; extra == "google"
Provides-Extra: azure
Requires-Dist: azure-ai-formrecognizer>=3.3.0; extra == "azure"
Provides-Extra: search
Requires-Dist: tantivy<1.0.0,>=0.21.0; extra == "search"
Requires-Dist: rtree<3.0.0,>=1.2.0; extra == "search"
Requires-Dist: networkx<4.0.0,>=2.5.0; extra == "search"
Requires-Dist: rapidfuzz>=3.0.0; extra == "search"
Provides-Extra: anthropic
Requires-Dist: anthropic>=0.26.0; extra == "anthropic"
Provides-Extra: openai
Requires-Dist: openai>=1.0.1; extra == "openai"
Provides-Extra: aws
Requires-Dist: aioboto3>=13.1.0; extra == "aws"
Requires-Dist: boto3>=1.18.0; extra == "aws"
